tse_utils_db/__init__.py
tse_utils_db/tse_market.py
tse_utils_db-1.1.11.dist-info/METADATA
tse_utils_db-1.1.11.dist-info/WHEEL
tse_utils_db-1.1.11.dist-info/top_level.txt
tse_utils_db-1.1.11.dist-info/RECORD
