Metadata-Version: 2.1
Name: tse_utils_db
Version: 1.1.11
Summary: Database for Tehran Stock Exchange (TSE).
Author: Arka Equities & Securities
Author-email: info@arkaequities.com
Classifier: Programming Language :: Python :: 3
Classifier: Operating System :: POSIX :: Linux
Classifier: Operating System :: MacOS :: MacOS X
Classifier: Operating System :: Microsoft :: Windows
Requires-Dist: python-dotenv
Requires-Dist: SQLAlchemy
Requires-Dist: mysql-connector-python
